MANIFEST.in
README.rst
setup.py
cobe/__init__.py
cobe/model.py
cobe/source.py
cobe/testing.py
cobe/ueid.py
cobe/utility.py
python_cobe.egg-info/PKG-INFO
python_cobe.egg-info/SOURCES.txt
python_cobe.egg-info/dependency_links.txt
python_cobe.egg-info/requires.txt
python_cobe.egg-info/top_level.txt
tests/conftest.py
tests/test_model.py
tests/test_source.py
tests/test_testing.py
tests/test_ueid.py