Metadata-Version: 1.1
Name: python-cobe
Version: 0.2.2
Summary: A library to enable streaming of custom entities to Cobe.io from within any Python applications
Home-page: https://cobe.io/
Author: Abilisoft Ltd.
Author-email: info@cobe.io
License: MIT
Platform: UNKNOWN
Classifier: Development Status :: 4 - Beta
Classifier: Intended Audience :: Developers
Classifier: License :: OSI Approved :: MIT License
Classifier: Operating System :: OS Independent
Classifier: Programming Language :: Python :: 3.4
Classifier: Programming Language :: Python :: 3.5
Classifier: Topic :: System :: Monitoring
